{"cameraMode":{"drawMode":0,"name":"Shaded","section":"Shading Mode"},"sceneLighting":false,"audioPlay":false,"sceneViewState":{"m_AlwaysRefresh":false,"showFog":true,"showSkybox":false,"showFlares":true,"showImageEffects":true,"showParticleSystems":true,"showVisualEffectGraphs":true,"m_FxEnabled":true},"in2DMode":false,"pivot":{"x":5.440000534057617,"y":0.30000001192092898,"z":-9.630000114440918},"rotation":{"x":-0.022944563999772073,"y":-0.9489598274230957,"z":0.3063884675502777,"w":-0.07094595581293106},"size":7.088723659515381,"orthographic":false}